MANIFEST.in
requirements.txt
setup.cfg
setup.py
sklearn_template.egg-info/PKG-INFO
sklearn_template.egg-info/SOURCES.txt
sklearn_template.egg-info/dependency_links.txt
sklearn_template.egg-info/requires.txt
sklearn_template.egg-info/top_level.txt
template/__init__.py
template/template.py