Metadata-Version: 1.0
Name: sklearn-template
Version: 0.0.3
Summary: A template for scikit-learn compatible packages
Home-page: UNKNOWN
Author: Vighnesh Birodkar
Author-email: vighneshbirodkar@nyu.edu
License: UNKNOWN
Platform: UNKNOWN
